fontbro/__init__.py
fontbro/exceptions.py
fontbro/flags.py
fontbro/font.py
fontbro/math.py
fontbro/metadata.py
fontbro/py.typed
fontbro/subset.py
fontbro/utils.py
fontbro/data/family-classifications.json
fontbro/data/features.json
fontbro/data/unicode-blocks.json
fontbro/data/unicode-scripts.json
python_fontbro-0.26.1.dist-info/licenses/LICENSE.txt
python_fontbro-0.26.1.dist-info/METADATA
python_fontbro-0.26.1.dist-info/WHEEL
python_fontbro-0.26.1.dist-info/top_level.txt
python_fontbro-0.26.1.dist-info/RECORD
