Metadata-Version: 2.4
Name: python-fontbro
Version: 0.26.1
Summary: friendly font operations on top of fontTools.
Author-email: Fabio Caccamo <fabio.caccamo@gmail.com>
Maintainer-email: Fabio Caccamo <fabio.caccamo@gmail.com>
License: MIT License
Project-URL: Homepage, https://github.com/fabiocaccamo/python-fontbro
Project-URL: Download, https://github.com/fabiocaccamo/python-fontbro/releases
Project-URL: Documentation, https://github.com/fabiocaccamo/python-fontbro#readme
Project-URL: Issues, https://github.com/fabiocaccamo/python-fontbro/issues
Project-URL: Funding, https://github.com/sponsors/fabiocaccamo/
Project-URL: Twitter, https://twitter.com/fabiocaccamo
Keywords: font,fonttools,languages,opentype,otf,python,scripts,slicing,subset,subsetting,ttf,unicode,utility,variable,variations,woff,woff2,wrapper,writing-systems
Classifier: Development Status :: 5 - Production/Stable
Classifier: Environment :: Console
Classifier: Environment :: Other Environment
Classifier: Environment :: Web Environment
Classifier: Intended Audience :: Developers
Classifier: Intended Audience :: End Users/Desktop
Classifier: License :: OSI Approved :: MIT License
Classifier: Natural Language :: English
Classifier: Operating System :: OS Independent
Classifier: Programming Language :: Python :: 3
Classifier: Programming Language :: Python :: 3.10
Classifier: Programming Language :: Python :: 3.11
Classifier: Programming Language :: Python :: 3.12
Classifier: Programming Language :: Python :: 3.13
Classifier: Programming Language :: Python :: 3.14
Classifier: Programming Language :: Python :: Implementation :: PyPy
Classifier: Topic :: Text Processing :: Fonts
Classifier: Topic :: Multimedia :: Graphics
Classifier: Topic :: Multimedia :: Graphics :: Graphics Conversion
License-File: LICENSE.txt
Requires-Dist: fonttools[lxml,pathops,unicode,woff]<5.0,>=4.43.0
Requires-Dist: imagehash<5.0.0,>=4.2.1
Requires-Dist: opentype-sanitizer<10.0.0,>=9.1.0
Requires-Dist: pillow<13.0.0,>=8.4.0
Requires-Dist: python-fsutil<1.0.0,>=0.16.0
Dynamic: license-file
